{
	"@context": "https://hubmapconsortium.github.io/ccf-ontology/ccf-context.jsonld",
	"@id": "https://purl.humanatlas.io/millitome/generic-ovary-female-left#61",
	"@type": "SpatialEntity",
	"creator": "Gokul Kaarthick Shanmugam",
	"creator_first_name": "Gokul Kaarthick",
	"creator_last_name": "Shanmugam",
	"creator_orcid": "https://orcid.org/0009-0004-9655-9278",
	"label": "61",
	"creation_date": "2025-02-11",
	"dimension_units": "millimeter",
	"placement": {
		"@context": "https://hubmapconsortium.github.io/ccf-ontology/ccf-context.jsonld",
		"@id": "https://purl.humanatlas.io/millitome/generic-ovary-female-left#61_placement",
		"@type": "SpatialPlacement",
		"target": "http://purl.org/ccf/latest/ccf.owl#VHFLeftOvary",
		"placement_date": "2025-02-11",
		"scaling_units": "ratio",
		"rotation_order": "XYZ",
		"rotation_units": "degree",
		"translation_units": "millimeter",
		"x_scaling": 1.0,
		"y_scaling": 1.0,
		"z_scaling": 1.0,
		"x_rotation": 0.0,
		"y_rotation": 0.0,
		"z_rotation": 0.0,
		"x_translation": 8.215066715294123,
		"y_translation": -0.9379503161542936,
		"z_translation": 10.618360074551084
	},
	"x_dimension": 0.03093924592427466,
	"y_dimension": 0.016734409509326642,
	"z_dimension": 0.004896765129762393
}